alicebot/__init__.py
alicebot/bot.py
alicebot/config.py
alicebot/dependencies.py
alicebot/event.py
alicebot/exceptions.py
alicebot/log.py
alicebot/message.py
alicebot/plugin.py
alicebot/py.typed
alicebot/typing.py
alicebot/utils.py
alicebot/adapter/__init__.py
alicebot/adapter/utils.py
alicebot-0.11.0.dist-info/METADATA
alicebot-0.11.0.dist-info/WHEEL
alicebot-0.11.0.dist-info/licenses/LICENSE
alicebot-0.11.0.dist-info/RECORD
