Metadata-Version: 2.3
Name: alicebot
Version: 0.11.0
Summary: A simply asynchronous python chatbot framework.
Project-URL: Homepage, https://docs.alicebot.dev/
Project-URL: Documentation, https://docs.alicebot.dev/
Project-URL: Repository, https://github.com/AliceBotProject/alicebot
Project-URL: Changelog, https://docs.alicebot.dev/changelog.html
Author-email: st1020 <stone_1020@qq.com>
License: MIT
License-File: LICENSE
Keywords: bot,chatbot,coolq,cqhttp,qq,qqbot
Classifier: Development Status :: 3 - Alpha
Classifier: Framework :: AsyncIO
Classifier: Framework :: Robot Framework
Classifier: Framework :: Robot Framework :: Library
Classifier: License :: OSI Approved :: MIT License
Classifier: Operating System :: OS Independent
Classifier: Programming Language :: Python :: 3
Classifier: Topic :: Communications :: Chat
Requires-Python: >=3.9
Requires-Dist: aiohttp<4.0.0,>=3.8.0
Requires-Dist: anyio<5.0.0,>=4.4.0
Requires-Dist: pydantic<3.0.0,>=2.0.3
Requires-Dist: rich<14.0.0,>=13.7.0
Requires-Dist: structlog<25.0.0,>=24.1.0
Requires-Dist: tomli<3.0.0,>=2.0.0; python_version < '3.11'
Requires-Dist: typing-extensions>=4.5.0
Provides-Extra: all
Requires-Dist: alicebot-adapter-apscheduler; extra == 'all'
Requires-Dist: alicebot-adapter-cqhttp; extra == 'all'
Requires-Dist: alicebot-adapter-dingtalk; extra == 'all'
Requires-Dist: alicebot-adapter-mirai; extra == 'all'
Requires-Dist: alicebot-adapter-onebot; extra == 'all'
Requires-Dist: alicebot-adapter-telegram; extra == 'all'
Requires-Dist: watchfiles>=0.24; extra == 'all'
Provides-Extra: apscheduler
Requires-Dist: alicebot-adapter-apscheduler; extra == 'apscheduler'
Provides-Extra: cqhttp
Requires-Dist: alicebot-adapter-cqhttp; extra == 'cqhttp'
Provides-Extra: dingtalk
Requires-Dist: alicebot-adapter-dingtalk; extra == 'dingtalk'
Provides-Extra: hot-reload
Requires-Dist: watchfiles>=0.24; extra == 'hot-reload'
Provides-Extra: mirai
Requires-Dist: alicebot-adapter-mirai; extra == 'mirai'
Provides-Extra: onebot
Requires-Dist: alicebot-adapter-onebot; extra == 'onebot'
Provides-Extra: telegram
Requires-Dist: alicebot-adapter-telegram; extra == 'telegram'
